tb/axi4l_behavioral_slave.v
// ============================================================
// Module      : axi4l_behavioral_slave
// Project     : core_axi_adapter - Tesla AI Hardware Portfolio
// Author      : Mayank
// Description : Deliberately NOT same-cycle: introduces a couple of wait
//               states on each channel before asserting *ready/*valid, so
//               the adapter under test is actually exercised as a real
//               multi-cycle bus master, not accidentally validated only
//               against an idealized same-cycle responder. Small RAM
//               behind it so read-back can be checked directly.
// ============================================================

module axi4l_behavioral_slave #(
    parameter AW = 16,
    parameter DW = 32,
    parameter AW_DELAY = 2,   // cycles awvalid/arvalid must wait before *ready
    parameter B_DELAY  = 1,   // cycles after write-accept before bvalid
    parameter R_DELAY  = 2    // cycles after read-accept before rvalid
)(
    input  wire            clk,
    input  wire            rst_n,

    input  wire [AW-1:0]   s_awaddr,
    input  wire             s_awvalid,
    output reg              s_awready,
    input  wire [DW-1:0]    s_wdata,
    input  wire [DW/8-1:0]  s_wstrb,
    input  wire             s_wvalid,
    output reg              s_wready,
    output reg  [1:0]       s_bresp,
    output reg              s_bvalid,
    input  wire             s_bready,
    input  wire [AW-1:0]    s_araddr,
    input  wire             s_arvalid,
    output reg              s_arready,
    output reg  [DW-1:0]    s_rdata,
    output reg  [1:0]       s_rresp,
    output reg              s_rvalid,
    input  wire             s_rready
);

reg [DW-1:0] mem [0:(1<<8)-1];   // small backing store, word-addressed on [7:0]

integer aw_cnt, ar_cnt;
reg aw_latched, ar_latched;
reg [AW-1:0] aw_addr_r, ar_addr_r;
reg w_latched;
reg [DW-1:0] w_data_r;

reg b_pending;
integer b_cnt;
reg r_pending;
integer r_cnt;

// ---- AW/W accept after AW_DELAY cycles of both being valid ------------
always @(posedge clk or negedge rst_n) begin
    if (!rst_n) begin
        s_awready <= 1'b0; s_wready <= 1'b0;
        aw_cnt <= 0; aw_latched <= 1'b0; w_latched <= 1'b0;
    end else begin
        s_awready <= 1'b0;
        s_wready  <= 1'b0;
        if (!aw_latched) begin
            if (s_awvalid) begin
                if (aw_cnt >= AW_DELAY) begin
                    s_awready  <= 1'b1;
                    aw_addr_r  <= s_awaddr;
                    aw_latched <= 1'b1;
                    aw_cnt     <= 0;
                end else aw_cnt <= aw_cnt + 1;
            end else aw_cnt <= 0;
        end
        if (!w_latched) begin
            if (s_wvalid) begin
                // piggy-back on the same delay counter for simplicity
                if (aw_cnt >= AW_DELAY || aw_latched) begin
                    s_wready  <= 1'b1;
                    w_data_r  <= s_wdata;
                    w_latched <= 1'b1;
                end
            end
        end
        if (aw_latched && w_latched) begin
            aw_latched <= 1'b0;
            w_latched  <= 1'b0;
        end
    end
end

// ---- B response B_DELAY cycles after both AW and W landed --------------
always @(posedge clk or negedge rst_n) begin
    if (!rst_n) begin
        s_bvalid <= 1'b0; s_bresp <= 2'b00; b_pending <= 1'b0; b_cnt <= 0;
    end else begin
        if (s_awready && s_wready) begin
            mem[aw_addr_r[7:0]] <= s_wdata;
            b_pending <= 1'b1;
            b_cnt <= 0;
        end else if (b_pending && !s_bvalid) begin
            if (b_cnt >= B_DELAY) begin
                s_bvalid <= 1'b1;
                s_bresp  <= 2'b00;
            end else b_cnt <= b_cnt + 1;
        end
        if (s_bvalid && s_bready) begin
            s_bvalid  <= 1'b0;
            b_pending <= 1'b0;
        end
    end
end

// ---- AR accept after AW_DELAY cycles -----------------------------------
always @(posedge clk or negedge rst_n) begin
    if (!rst_n) begin
        s_arready <= 1'b0; ar_cnt <= 0;
    end else begin
        s_arready <= 1'b0;
        if (s_arvalid && !r_pending) begin
            if (ar_cnt >= AW_DELAY) begin
                s_arready <= 1'b1;
                ar_addr_r <= s_araddr;
                ar_cnt    <= 0;
            end else ar_cnt <= ar_cnt + 1;
        end else if (!s_arvalid) ar_cnt <= 0;
    end
end

// ---- R response R_DELAY cycles after AR accepted -----------------------
always @(posedge clk or negedge rst_n) begin
    if (!rst_n) begin
        s_rvalid <= 1'b0; s_rresp <= 2'b00; r_pending <= 1'b0; r_cnt <= 0; s_rdata <= {DW{1'b0}};
    end else begin
        if (s_arready) begin
            r_pending <= 1'b1;
            r_cnt <= 0;
        end else if (r_pending && !s_rvalid) begin
            if (r_cnt >= R_DELAY) begin
                s_rvalid <= 1'b1;
                s_rdata  <= mem[ar_addr_r[7:0]];
                s_rresp  <= 2'b00;
            end else r_cnt <= r_cnt + 1;
        end
        if (s_rvalid && s_rready) begin
            s_rvalid  <= 1'b0;
            r_pending <= 1'b0;
        end
    end
end

endmodule

rtl/core_axi_adapter.v
// ============================================================
// Module      : core_axi_adapter
// Project     : core_axi_adapter - Tesla AI Hardware Portfolio
// Author      : Mayank
// Description : Converts riscv_ooo_core's dmem req/ready handshake
//               (dmem_addr/dmem_req/dmem_we/dmem_wdata/dmem_rdata/
//               dmem_ready - see riscv_ooo_core/rtl/lsu_frontend.v) into a
//               single-outstanding-transaction AXI4-Lite MASTER, so the
//               core's data-side memory accesses become bus-mastered
//               reads/writes reaching whatever a crossbar routes them to
//               (peripheral CSRs, a scratch RAM, etc).
//
//               This is why riscv_ooo_core's dmem interface grew the
//               dmem_req/dmem_ready handshake in the first place: the
//               original same-cycle interface (fine for a testbench's
//               behavioral RAM) can never be satisfied by a real AXI
//               transaction, which needs at least an address phase and a
//               data/response phase.
//
//               One request outstanding at a time (matches riscv_ooo_core's
//               own execution model - it never issues a second memory
//               request before the first completes, so there is nothing to
//               pipeline here). AW and W are issued together and accepted
//               independently (whichever of AWREADY/WREADY arrives first is
//               latched and held) - the same proven pattern used throughout
//               this portfolio's AXI4-Lite slaves (csr_block.v,
//               axi4s_dma.v, axi4l_slave_if.v), mirrored here from the
//               master side.
// ============================================================

module core_axi_adapter #(
    parameter AW = 16,   // AXI address width (matches the crossbar's master port)
    parameter DW = 32
)(
    input  wire            clk,
    input  wire            rst_n,

    // ---- riscv_ooo_core dmem port (slave side, from the core's POV) ----
    input  wire [AW-1:0]   dmem_addr,
    input  wire            dmem_req,
    input  wire            dmem_we,
    input  wire [DW-1:0]   dmem_wdata,
    output reg  [DW-1:0]   dmem_rdata,
    output wire             dmem_ready,   // combinational (Mealy) - see note below

    // ---- AXI4-Lite master (to the crossbar) ----
    output reg  [AW-1:0]   m_awaddr,
    output reg              m_awvalid,
    input  wire             m_awready,
    output reg  [DW-1:0]    m_wdata,
    output reg  [DW/8-1:0]  m_wstrb,
    output reg              m_wvalid,
    input  wire             m_wready,
    input  wire [1:0]       m_bresp,
    input  wire             m_bvalid,
    output reg              m_bready,
    output reg  [AW-1:0]    m_araddr,
    output reg              m_arvalid,
    input  wire             m_arready,
    input  wire [DW-1:0]    m_rdata,
    input  wire [1:0]       m_rresp,
    input  wire             m_rvalid,
    output reg              m_rready
);

localparam [2:0] ST_IDLE       = 3'd0,
                  ST_WRITE_ADDR = 3'd1,   // AW/W outstanding (independently)
                  ST_WRITE_RESP = 3'd2,   // waiting for B
                  ST_READ_ADDR  = 3'd3,   // AR outstanding
                  ST_READ_DATA  = 3'd4,   // waiting for R
                  ST_DONE       = 3'd5;   // 1-cycle dmem_ready pulse

reg [2:0] state;
reg       aw_done, w_done;

always @(posedge clk or negedge rst_n) begin
    if (!rst_n) begin
        state      <= ST_IDLE;
        aw_done    <= 1'b0;
        w_done     <= 1'b0;
        m_awvalid  <= 1'b0;
        m_wvalid   <= 1'b0;
        m_bready   <= 1'b0;
        m_arvalid  <= 1'b0;
        m_rready   <= 1'b0;
        m_awaddr   <= {AW{1'b0}};
        m_wdata    <= {DW{1'b0}};
        m_wstrb    <= {(DW/8){1'b0}};
        m_araddr   <= {AW{1'b0}};
        dmem_rdata <= {DW{1'b0}};
    end else begin
        case (state)
            ST_IDLE: begin
                if (dmem_req && dmem_we) begin
                    m_awaddr  <= dmem_addr;
                    m_awvalid <= 1'b1;
                    m_wdata   <= dmem_wdata;
                    m_wstrb   <= {(DW/8){1'b1}};
                    m_wvalid  <= 1'b1;
                    aw_done   <= 1'b0;
                    w_done    <= 1'b0;
                    state     <= ST_WRITE_ADDR;
                end else if (dmem_req && !dmem_we) begin
                    m_araddr  <= dmem_addr;
                    m_arvalid <= 1'b1;
                    state     <= ST_READ_ADDR;
                end
            end

            ST_WRITE_ADDR: begin
                if (m_awvalid && m_awready) begin
                    m_awvalid <= 1'b0;
                    aw_done   <= 1'b1;
                end
                if (m_wvalid && m_wready) begin
                    m_wvalid <= 1'b0;
                    w_done   <= 1'b1;
                end
                // Both halves accepted (this cycle or a previous one) -> move on.
                if ((aw_done || (m_awvalid && m_awready)) &&
                    (w_done  || (m_wvalid  && m_wready))) begin
                    m_bready <= 1'b1;
                    state    <= ST_WRITE_RESP;
                end
            end

            ST_WRITE_RESP: begin
                if (m_bvalid && m_bready) begin
                    m_bready <= 1'b0;
                    state    <= ST_DONE;
                    // m_bresp is available here if error reporting is ever
                    // wired up - not consumed today (dmem has no error port).
                end
            end

            ST_READ_ADDR: begin
                if (m_arvalid && m_arready) begin
                    m_arvalid <= 1'b0;
                    m_rready  <= 1'b1;
                    state     <= ST_READ_DATA;
                end
            end

            ST_READ_DATA: begin
                if (m_rvalid && m_rready) begin
                    m_rready   <= 1'b0;
                    dmem_rdata <= m_rdata;
                    state      <= ST_DONE;
                end
            end

            ST_DONE: begin
                state <= ST_IDLE;
            end

            default: state <= ST_IDLE;
        endcase
    end
end

// Bug found via tb_core_axi_adapter.v (back-to-back write/write/read/read,
// zero idle cycles, req held as a real clocked register exactly like
// lsu_frontend's req_outstanding_r): dmem_ready was originally a
// REGISTERED pulse, asserted the cycle AFTER state left ST_DONE for
// ST_IDLE. That one-cycle lag meant ST_IDLE's "is this a fresh request"
// check could see dmem_req still asserted (the core hadn't yet observed
// dmem_ready and dropped its own request register) and start a SECOND,
// spurious transaction with stale address/data - confirmed empirically:
// 3 AW-channel accepts for 2 real writes, and subsequent reads came back
// shifted/wrong. Making dmem_ready a combinational (Mealy) output tied
// directly to `state == ST_DONE` removes the lag entirely: the adapter
// and the requester's own req-clearing logic now observe completion on
// the exact same cycle, so ST_IDLE can never see a stale request that
// dmem_ready itself just explained.
assign dmem_ready = (state == ST_DONE);

endmodule

tb/tb_core_axi_adapter.v
// ============================================================
// Testbench  : tb_core_axi_adapter
// Project    : core_axi_adapter - Tesla AI Hardware Portfolio
// Author     : Mayank
// Description: Drives the adapter's dmem-side port with a REGISTERED
//              request signal that mirrors riscv_ooo_core's lsu_frontend.v
//              req_outstanding_r EXACTLY (a clocked reg that sets on a new
//              request and clears via non-blocking assignment the cycle
//              AFTER dmem_ready is observed - never nudged mid-cycle by a
//              blocking assign), presented back-to-back with ZERO idle
//              cycles between requests - the strictest case for catching a
//              suspected bug: if the adapter's internal state returns to
//              idle in a way that overlaps with the core's request signal
//              still being asserted (leftover from the request that JUST
//              completed), it could spuriously start a second, unwanted
//              transaction using stale address/data.
//
//              An earlier version of this testbench drove dmem_req via a
//              task with a blocking assignment at a negedge - which
//              (correctly, per the negedge-timing lessons learned earlier
//              this session) avoids posedge races, but ALSO happens to
//              drop dmem_req half a cycle earlier than a real clocked
//              register would, silently avoiding the exact hazard window
//              this test exists to check. Fixed by driving dmem_req from
//              an actual posedge-clocked always block instead.
//
//              Sequence: WRITE addr=5<-100, WRITE addr=6<-200,
//              READ addr=5 (expect 100), READ addr=6 (expect 200), all
//              back-to-back. Independently counts every AW-accept and
//              AR-accept on the slave side and requires EXACTLY 2 of each
//              - a stray 3rd accept on either channel means a spurious
//              duplicate fired.
// ============================================================

`timescale 1ns/1ps

module tb_core_axi_adapter;

localparam AW = 16;
localparam DW = 32;

reg clk, rst_n;

wire [AW-1:0] dmem_addr;
wire          dmem_req;
wire          dmem_we;
wire [DW-1:0] dmem_wdata;
wire [DW-1:0] dmem_rdata;
wire          dmem_ready;

wire [AW-1:0] m_awaddr;
wire          m_awvalid, m_awready;
wire [DW-1:0] m_wdata;
wire [DW/8-1:0] m_wstrb;
wire          m_wvalid, m_wready;
wire [1:0]    m_bresp;
wire          m_bvalid, m_bready;
wire [AW-1:0] m_araddr;
wire          m_arvalid, m_arready;
wire [DW-1:0] m_rdata;
wire [1:0]    m_rresp;
wire          m_rvalid, m_rready;

core_axi_adapter #(.AW(AW), .DW(DW)) dut (
    .clk(clk), .rst_n(rst_n),
    .dmem_addr(dmem_addr), .dmem_req(dmem_req), .dmem_we(dmem_we),
    .dmem_wdata(dmem_wdata), .dmem_rdata(dmem_rdata), .dmem_ready(dmem_ready),
    .m_awaddr(m_awaddr), .m_awvalid(m_awvalid), .m_awready(m_awready),
    .m_wdata(m_wdata), .m_wstrb(m_wstrb), .m_wvalid(m_wvalid), .m_wready(m_wready),
    .m_bresp(m_bresp), .m_bvalid(m_bvalid), .m_bready(m_bready),
    .m_araddr(m_araddr), .m_arvalid(m_arvalid), .m_arready(m_arready),
    .m_rdata(m_rdata), .m_rresp(m_rresp), .m_rvalid(m_rvalid), .m_rready(m_rready)
);

axi4l_behavioral_slave #(.AW(AW), .DW(DW), .AW_DELAY(2), .B_DELAY(1), .R_DELAY(2)) slave (
    .clk(clk), .rst_n(rst_n),
    .s_awaddr(m_awaddr), .s_awvalid(m_awvalid), .s_awready(m_awready),
    .s_wdata(m_wdata), .s_wstrb(m_wstrb), .s_wvalid(m_wvalid), .s_wready(m_wready),
    .s_bresp(m_bresp), .s_bvalid(m_bvalid), .s_bready(m_bready),
    .s_araddr(m_araddr), .s_arvalid(m_arvalid), .s_arready(m_arready),
    .s_rdata(m_rdata), .s_rresp(m_rresp), .s_rvalid(m_rvalid), .s_rready(m_rready)
);

initial clk = 1'b0;
always #5 clk = ~clk;

initial begin
    $dumpfile("sim/tb_core_axi_adapter.vcd");
    $dumpvars(0, tb_core_axi_adapter);
end

// ---- Independent transaction counters (slave-side accepts) -------------
integer aw_accepts, ar_accepts;
always @(posedge clk) begin
    if (!rst_n) begin
        aw_accepts <= 0;
        ar_accepts <= 0;
    end else begin
        if (m_awvalid && m_awready) aw_accepts <= aw_accepts + 1;
        if (m_arvalid && m_arready) ar_accepts <= ar_accepts + 1;
    end
end

// ---- Fake-core driver: a REAL clocked register, exactly mirroring
//      lsu_frontend's req_outstanding_r (sets on a new queued request,
//      clears via non-blocking assign the cycle after dmem_ready, never
//      touched by a blocking assign) -------------------------------------
localparam NREQ = 4;
reg [AW-1:0] q_addr   [0:NREQ-1];
reg          q_we     [0:NREQ-1];
reg [DW-1:0] q_wdata  [0:NREQ-1];
reg          q_is_read[0:NREQ-1];
reg [DW-1:0] q_expect [0:NREQ-1];
integer q_head;

reg          dmem_req_r;
reg [AW-1:0] dmem_addr_r;
reg          dmem_we_r;
reg [DW-1:0] dmem_wdata_r;

assign dmem_req   = dmem_req_r;
assign dmem_addr  = dmem_addr_r;
assign dmem_we    = dmem_we_r;
assign dmem_wdata = dmem_wdata_r;

integer errors;

always @(posedge clk or negedge rst_n) begin
    if (!rst_n) begin
        dmem_req_r <= 1'b0;
        q_head     <= 0;
    end else begin
        if (dmem_req_r && dmem_ready) begin
            // Check a read's result the exact cycle completion is seen.
            if (q_is_read[q_head]) begin
                if (dmem_rdata !== q_expect[q_head]) begin
                    $display("[%0t] ERROR: read addr=%0d got %0d, expected %0d",
                              $time, q_addr[q_head], dmem_rdata, q_expect[q_head]);
                    errors = errors + 1;
                end else begin
                    $display("[%0t] OK: read addr=%0d = %0d", $time, q_addr[q_head], dmem_rdata);
                end
            end
            dmem_req_r <= 1'b0;
            q_head     <= q_head + 1;
        end else if (!dmem_req_r && (q_head < NREQ)) begin
            dmem_req_r    <= 1'b1;
            dmem_addr_r   <= q_addr[q_head];
            dmem_we_r     <= q_we[q_head];
            dmem_wdata_r  <= q_wdata[q_head];
        end
    end
end

initial begin
    rst_n = 1'b0;
    errors = 0;

    q_addr[0]=16'd5; q_we[0]=1'b1; q_wdata[0]=32'd100; q_is_read[0]=1'b0; q_expect[0]=32'd0;
    q_addr[1]=16'd6; q_we[1]=1'b1; q_wdata[1]=32'd200; q_is_read[1]=1'b0; q_expect[1]=32'd0;
    q_addr[2]=16'd5; q_we[2]=1'b0; q_wdata[2]=32'd0;   q_is_read[2]=1'b1; q_expect[2]=32'd100;
    q_addr[3]=16'd6; q_we[3]=1'b0; q_wdata[3]=32'd0;   q_is_read[3]=1'b1; q_expect[3]=32'd200;

    repeat (4) @(negedge clk);
    rst_n = 1'b1;

    wait (q_head == NREQ);
    repeat (10) @(negedge clk);

    $display("==============================================");
    if (aw_accepts !== 2) begin
        $display("[%0t] ERROR: expected exactly 2 AW accepts, saw %0d (spurious duplicate write!)", $time, aw_accepts);
        errors = errors + 1;
    end else begin
        $display("[%0t] OK: exactly 2 AW accepts, no duplicate writes", $time);
    end
    if (ar_accepts !== 2) begin
        $display("[%0t] ERROR: expected exactly 2 AR accepts, saw %0d (spurious duplicate read!)", $time, ar_accepts);
        errors = errors + 1;
    end else begin
        $display("[%0t] OK: exactly 2 AR accepts, no duplicate reads", $time);
    end

    if (errors == 0)
        $display("TB_CORE_AXI_ADAPTER: PASS (0 errors)");
    else
        $display("TB_CORE_AXI_ADAPTER: FAIL (%0d errors)", errors);
    $display("==============================================");
    $finish;
end

initial begin
    #100000;
    $display("[%0t] ERROR: global timeout (q_head stuck?)", $time);
    $display("TB_CORE_AXI_ADAPTER: FAIL (timeout)");
    $finish;
end

endmodule

sim/tb_core_axi_adapter.vcd
$date
	Sun Jul 19 10:43:15 2026
$end
$version
	Icarus Verilog
$end
$timescale
	1ps
$end
$scope module tb_core_axi_adapter $end
$var wire 16 ! dmem_addr [15:0] $end
$var wire 1 " dmem_req $end
$var wire 32 # dmem_wdata [31:0] $end
$var wire 1 $ dmem_we $end
$var wire 1 % m_wvalid $end
$var wire 4 & m_wstrb [3:0] $end
$var wire 1 ' m_wready $end
$var wire 32 ( m_wdata [31:0] $end
$var wire 1 ) m_rvalid $end
$var wire 2 * m_rresp [1:0] $end
$var wire 1 + m_rready $end
$var wire 32 , m_rdata [31:0] $end
$var wire 1 - m_bvalid $end
$var wire 2 . m_bresp [1:0] $end
$var wire 1 / m_bready $end
$var wire 1 0 m_awvalid $end
$var wire 1 1 m_awready $end
$var wire 16 2 m_awaddr [15:0] $end
$var wire 1 3 m_arvalid $end
$var wire 1 4 m_arready $end
$var wire 16 5 m_araddr [15:0] $end
$var wire 1 6 dmem_ready $end
$var wire 32 7 dmem_rdata [31:0] $end
$var parameter 32 8 AW $end
$var parameter 32 9 DW $end
$var parameter 32 : NREQ $end
$var reg 1 ; clk $end
$var reg 16 < dmem_addr_r [15:0] $end
$var reg 1 = dmem_req_r $end
$var reg 32 > dmem_wdata_r [31:0] $end
$var reg 1 ? dmem_we_r $end
$var reg 1 @ rst_n $end
$var integer 32 A ar_accepts [31:0] $end
$var integer 32 B aw_accepts [31:0] $end
$var integer 32 C errors [31:0] $end
$var integer 32 D q_head [31:0] $end
$scope module dut $end
$var wire 1 ; clk $end
$var wire 16 E dmem_addr [15:0] $end
$var wire 1 " dmem_req $end
$var wire 32 F dmem_wdata [31:0] $end
$var wire 1 $ dmem_we $end
$var wire 1 @ rst_n $end
$var wire 1 ' m_wready $end
$var wire 1 ) m_rvalid $end
$var wire 2 G m_rresp [1:0] $end
$var wire 32 H m_rdata [31:0] $end
$var wire 1 - m_bvalid $end
$var wire 2 I m_bresp [1:0] $end
$var wire 1 1 m_awready $end
$var wire 1 4 m_arready $end
$var wire 1 6 dmem_ready $end
$var parameter 32 J AW $end
$var parameter 32 K DW $end
$var parameter 3 L ST_DONE $end
$var parameter 3 M ST_IDLE $end
$var parameter 3 N ST_READ_ADDR $end
$var parameter 3 O ST_READ_DATA $end
$var parameter 3 P ST_WRITE_ADDR $end
$var parameter 3 Q ST_WRITE_RESP $end
$var reg 1 R aw_done $end
$var reg 32 S dmem_rdata [31:0] $end
$var reg 16 T m_araddr [15:0] $end
$var reg 1 3 m_arvalid $end
$var reg 16 U m_awaddr [15:0] $end
$var reg 1 0 m_awvalid $end
$var reg 1 / m_bready $end
$var reg 1 + m_rready $end
$var reg 32 V m_wdata [31:0] $end
$var reg 4 W m_wstrb [3:0] $end
$var reg 1 % m_wvalid $end
$var reg 3 X state [2:0] $end
$var reg 1 Y w_done $end
$upscope $end
$scope module slave $end
$var wire 1 ; clk $end
$var wire 1 @ rst_n $end
$var wire 16 Z s_araddr [15:0] $end
$var wire 1 3 s_arvalid $end
$var wire 16 [ s_awaddr [15:0] $end
$var wire 1 0 s_awvalid $end
$var wire 1 / s_bready $end
$var wire 1 + s_rready $end
$var wire 32 \ s_wdata [31:0] $end
$var wire 4 ] s_wstrb [3:0] $end
$var wire 1 % s_wvalid $end
$var parameter 32 ^ AW $end
$var parameter 32 _ AW_DELAY $end
$var parameter 32 ` B_DELAY $end
$var parameter 32 a DW $end
$var parameter 32 b R_DELAY $end
$var reg 16 c ar_addr_r [15:0] $end
$var reg 16 d aw_addr_r [15:0] $end
$var reg 1 e aw_latched $end
$var reg 1 f b_pending $end
$var reg 1 g r_pending $end
$var reg 1 4 s_arready $end
$var reg 1 1 s_awready $end
$var reg 2 h s_bresp [1:0] $end
$var reg 1 - s_bvalid $end
$var reg 32 i s_rdata [31:0] $end
$var reg 2 j s_rresp [1:0] $end
$var reg 1 ) s_rvalid $end
$var reg 1 ' s_wready $end
$var reg 32 k w_data_r [31:0] $end
$var reg 1 l w_latched $end
$var integer 32 m ar_cnt [31:0] $end
$var integer 32 n aw_cnt [31:0] $end
$var integer 32 o b_cnt [31:0] $end
$var integer 32 p r_cnt [31:0] $end
$upscope $end
$upscope $end
$enddefinitions $end
$comment Show the parameter values. $end
$dumpall
b10 b
b100000 a
b1 `
b10 _
b10000 ^
b10 Q
b1 P
b100 O
b11 N
b0 M
b101 L
b100000 K
b10000 J
b100 :
b100000 9
b10000 8
$end
#0
$dumpvars
b0 p
b0 o
b0 n
b0 m
0l
bx k
b0 j
b0 i
b0 h
0g
0f
0e
bx d
bx c
b0 ]
b0 \
b0 [
b0 Z
0Y
b0 X
b0 W
b0 V
b0 U
b0 T
b0 S
0R
b0 I
b0 H
b0 G
bx F
bx E
b0 D
b0 C
bx B
bx A
0@
x?
bx >
0=
bx <
0;
b0 7
06
b0 5
04
03
b0 2
01
00
0/
b0 .
0-
b0 ,
0+
b0 *
0)
b0 (
0'
b0 &
0%
x$
bx #
0"
bx !
$end
#5000
b0 A
b0 B
1;
#10000
0;
#15000
1;
#20000
0;
#25000
1;
#30000
0;
#35000
1;
#40000
1@
0;
#45000
b1100100 #
b1100100 F
b1100100 >
1$
1?
b101 !
b101 E
b101 <
1"
1=
1;
#50000
0;
#55000
b1 X
1%
b1111 &
b1111 W
b1111 ]
b1100100 (
b1100100 V
b1100100 \
10
b101 2
b101 U
b101 [
1;
#60000
0;
#65000
b1 n
1;
#70000
0;
#75000
b10 n
1;
#80000
0;
#85000
1l
b1100100 k
1'
b0 n
1e
b101 d
11
1;
#90000
0;
#95000
b10 X
1/
1Y
0%
1R
00
0l
0e
0'
01
1f
b1 B
1;
#100000
0;
#105000
b1 o
1;
#110000
0;
#115000
1-
1;
#120000
0;
#125000
0f
0-
16
b101 X
0/
1;
#130000
0;
#135000
06
b0 X
b1 D
0"
0=
1;
#140000
0;
#145000
b11001000 #
b11001000 F
b11001000 >
b110 !
b110 E
b110 <
1"
1=
1;
#150000
0;
#155000
b1 X
0Y
0R
1%
b11001000 (
b11001000 V
b11001000 \
10
b110 2
b110 U
b110 [
1;
#160000
0;
#165000
b1 n
1;
#170000
0;
#175000
b10 n
1;
#180000
0;
#185000
1l
b11001000 k
1'
b0 n
1e
b110 d
11
1;
#190000
0;
#195000
b10 X
1/
1Y
0%
1R
00
0l
0e
0'
01
b0 o
1f
b10 B
1;
#200000
0;
#205000
b1 o
1;
#210000
0;
#215000
1-
1;
#220000
0;
#225000
0f
0-
16
b101 X
0/
1;
#230000
0;
#235000
06
b0 X
b10 D
0"
0=
1;
#240000
0;
#245000
b0 #
b0 F
b0 >
0$
0?
b101 !
b101 E
b101 <
1"
1=
1;
#250000
0;
#255000
b11 X
13
b101 5
b101 T
b101 Z
1;
#260000
0;
#265000
b1 m
1;
#270000
0;
#275000
b10 m
1;
#280000
0;
#285000
b0 m
b101 c
14
1;
#290000
0;
#295000
b100 X
1+
03
b1 m
04
1g
b1 A
1;
#300000
0;
#305000
b1 p
b0 m
1;
#310000
0;
#315000
b10 p
1;
#320000
0;
#325000
b1100100 ,
b1100100 H
b1100100 i
1)
1;
#330000
0;
#335000
16
b101 X
b1100100 7
b1100100 S
0+
0g
0)
1;
#340000
0;
#345000
b11 D
0"
0=
06
b0 X
1;
#350000
0;
#355000
b110 !
b110 E
b110 <
1"
1=
1;
#360000
0;
#365000
b11 X
13
b110 5
b110 T
b110 Z
1;
#370000
0;
#375000
b1 m
1;
#380000
0;
#385000
b10 m
1;
#390000
0;
#395000
b0 m
b110 c
14
1;
#400000
0;
#405000
b0 p
1g
b1 m
04
b100 X
1+
03
b10 A
1;
#410000
0;
#415000
b0 m
b1 p
1;
#420000
0;
#425000
b10 p
1;
#430000
0;
#435000
b11001000 ,
b11001000 H
b11001000 i
1)
1;
#440000
0;
#445000
0g
0)
16
b101 X
b11001000 7
b11001000 S
0+
1;
#450000
0;
#455000
06
b0 X
b100 D
0"
0=
1;
